DDownloader/__init__.py
DDownloader/bin/aria2c.exe
DDownloader/bin/ffmpeg.exe
DDownloader/bin/mkvmerge.exe
DDownloader/bin/mp4decrypt.exe
DDownloader/bin/N_m3u8DL-RE.exe
DDownloader/bin/shaka-packager.exe
DDownloader/bin/yt-dlp.exe
DDownloader/main.py
DDownloader/modules/__init__.py
DDownloader/modules/args_parser.py
DDownloader/modules/banners.py
DDownloader/modules/downloader.py
DDownloader/modules/helper.py
DDownloader/modules/streamlink.py
ddownloader-0.4.5.dist-info/entry_points.txt
ddownloader-0.4.5.dist-info/licenses/LICENSE
ddownloader-0.4.5.dist-info/METADATA
ddownloader-0.4.5.dist-info/WHEEL
ddownloader-0.4.5.dist-info/RECORD
