Metadata-Version: 2.4
Name: DDownloader
Version: 0.4.5
Summary: A downloader for DRM-protected & Non DRM-protected content.
License: MIT License
License-File: LICENSE
Author: ThatNotEasy
Author-email: apidotmy@proton.me
Requires-Python: >=3.7
Classifier: Programming Language :: Python :: 3
Classifier: Programming Language :: Python :: 3.7
Classifier: Programming Language :: Python :: 3.8
Classifier: Programming Language :: Python :: 3.9
Classifier: Programming Language :: Python :: 3.10
Classifier: Programming Language :: Python :: 3.11
Classifier: License :: OSI Approved :: MIT License
Classifier: Operating System :: OS Independent
Requires-Dist: colorama (>=0.4.5)
Requires-Dist: coloredlogs (>=15.0)
Requires-Dist: loguru (>=0.6.0)
Requires-Dist: pymediainfo (>=6.1.0,<7.0.0)
Requires-Dist: requests (>=2.26.0)
Requires-Dist: tqdm (>=4.64.0)
Project-URL: Homepage, https://github.com/ThatNotEasy/DDownloader
